wagtail_trash/__init__.py
wagtail_trash/apps.py
wagtail_trash/forms.py
wagtail_trash/managers.py
wagtail_trash/mixins.py
wagtail_trash/models.py
wagtail_trash/utils.py
wagtail_trash/version.py
wagtail_trash/views.py
wagtail_trash/wagtail_hooks.py
wagtail_trash/locale/en/LC_MESSAGES/django.mo
wagtail_trash/locale/en/LC_MESSAGES/django.po
wagtail_trash/locale/es_AR/LC_MESSAGES/django.mo
wagtail_trash/locale/es_AR/LC_MESSAGES/django.po
wagtail_trash/locale/pt_BR/LC_MESSAGES/django.mo
wagtail_trash/locale/pt_BR/LC_MESSAGES/django.po
wagtail_trash/locale/sv/LC_MESSAGES/django.mo
wagtail_trash/locale/sv/LC_MESSAGES/django.po
wagtail_trash/management/__init__.py
wagtail_trash/management/commands/__init__.py
wagtail_trash/management/commands/delete_stray_pages.py
wagtail_trash/management/commands/empty_trash.py
wagtail_trash/migrations/0001_initial.py
wagtail_trash/migrations/0002_translation.py
wagtail_trash/migrations/__init__.py
wagtail_trash/templates/wagtail_trash/index.html
wagtail_trash/templates/wagtail_trash/move.html
wagtail_trash-3.2.0.dist-info/licenses/LICENSE
wagtail_trash-3.2.0.dist-info/METADATA
wagtail_trash-3.2.0.dist-info/WHEEL
wagtail_trash-3.2.0.dist-info/top_level.txt
wagtail_trash-3.2.0.dist-info/RECORD
