Metadata-Version: 2.4
Name: wagtail-trash
Version: 3.2.0
Summary: Make deleted pages only temporarily deleted.
Author: Andreas Bernacca
Author-email: ante.bernacca@gmail.com
License: MIT License
Project-URL: Source, https://github.com/Frojd/wagtail-trash/
Project-URL: Changelog, https://github.com/Frojd/wagtail-trash/blob/main/CHANGELOG.md
Classifier: Environment :: Web Environment
Classifier: Intended Audience :: Developers
Classifier: Operating System :: OS Independent
Classifier: Programming Language :: Python
Classifier: Programming Language :: Python :: 3
Classifier: Programming Language :: Python :: 3.9
Classifier: Programming Language :: Python :: 3.10
Classifier: Programming Language :: Python :: 3.11
Classifier: Programming Language :: Python :: 3.12
Classifier: Programming Language :: Python :: 3.13
Classifier: Framework :: Django
Classifier: Framework :: Django :: 4.2
Classifier: Framework :: Django :: 5.1
Classifier: Framework :: Django :: 5.2
Classifier: Framework :: Wagtail
Classifier: Framework :: Wagtail :: 6
Classifier: Framework :: Wagtail :: 7
Classifier: License :: OSI Approved :: MIT License
License-File: LICENSE
Requires-Dist: wagtail>=6.3
Requires-Dist: wagtail-modeladmin
Provides-Extra: testing
Requires-Dist: black; extra == "testing"
Requires-Dist: wagtail-factories; extra == "testing"
Dynamic: author
Dynamic: author-email
Dynamic: classifier
Dynamic: description
Dynamic: description-content-type
Dynamic: license
Dynamic: license-file
Dynamic: project-url
Dynamic: provides-extra
Dynamic: requires-dist
Dynamic: summary
